salp/__init__.py
salp/_version.py
salp/welcome.py
salp-0.0.1.dist-info/licenses/LICENSE
salp-0.0.1.dist-info/METADATA
salp-0.0.1.dist-info/WHEEL
salp-0.0.1.dist-info/top_level.txt
salp-0.0.1.dist-info/RECORD
